keycycle/__init__.py
keycycle/legacy_multi_provider_wrapper.py
keycycle/multi_client_wrapper.py
keycycle/py.typed
keycycle/utils.py
keycycle/adapters/__init__.py
keycycle/adapters/generic_adapter.py
keycycle/adapters/openai_adapter.py
keycycle/config/__init__.py
keycycle/config/constants.py
keycycle/config/dataclasses.py
keycycle/config/enums.py
keycycle/config/loader.py
keycycle/config/log_config.py
keycycle/config/models.py
keycycle/config/models/cerebras.yaml
keycycle/config/models/cohere.yaml
keycycle/config/models/gemini.yaml
keycycle/config/models/groq.yaml
keycycle/config/models/moonshot.yaml
keycycle/config/models/openrouter.yaml
keycycle/config/models/openrouter_models.yaml
keycycle/core/__init__.py
keycycle/core/backoff.py
keycycle/core/exceptions.py
keycycle/core/utils.py
keycycle/key_rotation/__init__.py
keycycle/key_rotation/rotating_mixin.py
keycycle/key_rotation/rotation_manager.py
keycycle/usage/__init__.py
keycycle/usage/db_logic.py
keycycle/usage/usage_logger.py
keycycle-0.2.4.dist-info/METADATA
keycycle-0.2.4.dist-info/WHEEL
keycycle-0.2.4.dist-info/top_level.txt
keycycle-0.2.4.dist-info/RECORD
