Metadata-Version: 2.4
Name: keycycle
Version: 0.2.4
Summary: A thread-safe key rotation and rate limiting manager for API keys.
Author-email: William Jin <jinwilliam.jin@gmail.com>
Classifier: Programming Language :: Python :: 3
Classifier: License :: OSI Approved :: MIT License
Classifier: Operating System :: OS Independent
Classifier: Development Status :: 3 - Alpha
Requires-Python: >=3.9
Requires-Dist: python-dotenv
Requires-Dist: sqlalchemy
Requires-Dist: pymysql
Requires-Dist: rich
Requires-Dist: PyYAML
Provides-Extra: openai
Requires-Dist: openai; extra == "openai"
Provides-Extra: agno
Requires-Dist: agno; extra == "agno"
Provides-Extra: cohere
Requires-Dist: cohere; extra == "cohere"
Provides-Extra: cerebras
Requires-Dist: cerebras-cloud-sdk; extra == "cerebras"
Provides-Extra: groq
Requires-Dist: groq; extra == "groq"
Provides-Extra: openrouter
Requires-Dist: openrouter; extra == "openrouter"
Provides-Extra: all
Requires-Dist: openai; extra == "all"
Requires-Dist: agno; extra == "all"
Requires-Dist: cohere; extra == "all"
Requires-Dist: cerebras-cloud-sdk; extra == "all"
Requires-Dist: groq; extra == "all"
Requires-Dist: openrouter; extra == "all"
Provides-Extra: test
Requires-Dist: pytest>=7.4.0; extra == "test"
Requires-Dist: pytest-cov>=4.1.0; extra == "test"
Requires-Dist: pytest-asyncio>=0.21.0; extra == "test"
Requires-Dist: pytest-timeout>=2.2.0; extra == "test"
Provides-Extra: dev
Requires-Dist: keycycle[test]; extra == "dev"
Requires-Dist: mypy>=1.5.0; extra == "dev"
Requires-Dist: types-PyYAML; extra == "dev"
